{
 "status": "success",
 "data": {
  "resultType": "matrix",
  "result": [
   {
    "metric": {
     "__name__": "node_memory_MemFree_bytes",
     "instance": "dmaf5.home:9100",
     "job": "node-exporter"
    },
    "values": [
     [
      1678066203.119,
      "1086185472"
     ],
     [
      1678066233.119,
      "1086185472"
     ],
     [
      1678066263.119,
      "1086185472"
     ],
     [
      1678066293.119,
      "1086185472"
     ],
     [
      1678066323.119,
      "1086185472"
     ],
     [
      1678066353.119,
      "1086185472"
     ],
     [
      1678066383.119,
      "1086185472"
     ],
     [
      1678066413.119,
      "1086185472"
     ],
     [
      1678066443.119,
      "1086185472"
     ],
     [
      1678066473.119,
      "1086185472"
     ]
    ]
   },
   {
    "metric": {
     "__name__": "node_memory_MemFree_bytes",
     "instance": "raspberrypi.home:9100",
     "job": "node-exporter"
    },
    "values": [
     [
      1678066203.119,
      "3210809344"
     ],
     [
      1678066233.119,
      "3210809344"
     ],
     [
      1678066263.119,
      "3210809344"
     ],
     [
      1678066293.119,
      "3210809344"
     ],
     [
      1678066323.119,
      "3210809344"
     ],
     [
      1678066353.119,
      "3210809344"
     ],
     [
      1678066383.119,
      "3210809344"
     ],
     [
      1678066413.119,
      "3210809344"
     ],
     [
      1678066443.119,
      "3210809344"
     ],
     [
      1678066473.119,
      "3210809344"
     ]
    ]
   }
  ]
 }
}